gpgraph/__init__.py
gpgraph/__version__.py
gpgraph/base.py
gpgraph/draw.py
gpgraph/matrices.py
gpgraph/models.py
gpgraph/paths.py
gpgraph/pyplot/__init__.py
gpgraph/pyplot/edges.py
gpgraph/pyplot/network.py
gpgraph/pyplot/nodes.py
gpgraph/pyplot/paths.py
gpgraph/pyplot/pos.py
gpgraph/pyplot/utils.py
gpgraph/tests/__init__.py
gpgraph/tests/test_base.py
gpgraph/tests/test_draw.py
gpgraph/tests/test_matrices.py
gpgraph/tests/test_models.py
gpgraph/tests/test_paths.py
gpgraph/tests/data/test_data.csv
gpgraph/tests/data/test_data.json
gpgraph-0.2.0.dist-info/LICENSE
gpgraph-0.2.0.dist-info/METADATA
gpgraph-0.2.0.dist-info/WHEEL
gpgraph-0.2.0.dist-info/top_level.txt
gpgraph-0.2.0.dist-info/RECORD
