Metadata-Version: 2.1
Name: gpgraph
Version: 0.2.0
Summary: NetworkX for genotype-phenotype maps.
Home-page: https://github.com/Zsailer/gpgraph
Author: Zach Sailer
Author-email: zachsailer@gmail.com
License: MIT
Platform: UNKNOWN
Classifier: Programming Language :: Python :: 3
Classifier: Programming Language :: Python :: 3.3
Classifier: Programming Language :: Python :: 3.4
Classifier: Programming Language :: Python :: 3.5
Classifier: Programming Language :: Python :: 3.6
Classifier: Programming Language :: Python :: Implementation :: CPython
Classifier: Programming Language :: Python :: Implementation :: PyPy
